venuspy/__init__.py
venuspy/cli.py
venuspy/initialSampling.py
venuspy/md.py
venuspy/calc/bagelcalc.py
venuspy/calc/chempotpycalc.py
venuspy/calc/minisgdmlcalc.py
venuspy/calc/mopaccalc.py
venuspy/calc/nwchemcalc.py
venuspy/calc/nwchemexcalc.py
venuspy/calc/original_nwchemexcalc.py
venuspy/calc/physnetcalc.py
venuspy/calc/psi4calc.py
venuspy/calc/qcengineGAMESScalc.py
venuspy/calc/xtbcalc.py
venuspython-1.1.2.dist-info/METADATA
venuspython-1.1.2.dist-info/WHEEL
venuspython-1.1.2.dist-info/entry_points.txt
venuspython-1.1.2.dist-info/top_level.txt
venuspython-1.1.2.dist-info/RECORD
