Metadata-Version: 2.4
Name: venuspython
Version: 1.1.2
Summary: VENUSpy Initial Sampling and Molecular Dynamics
Keywords: moleculardynamics,initialsampling
Classifier: Development Status :: 5 - Production/Stable
Classifier: Environment :: Console
Classifier: Intended Audience :: Science/Research
Classifier: Operating System :: OS Independent
Classifier: Programming Language :: Python :: 3
Requires-Python: >=3.7
